dseagull/__init__.py
dseagull/apps.py
dseagull/checks.py
dseagull/django.py
dseagull/djwt.py
dseagull/dlogging.py
dseagull/fields.py
dseagull/filters.py
dseagull/logger.py
dseagull/middleware.py
dseagull/models.py
dseagull/pagination.py
dseagull/sae.py
dseagull/serializers.py
dseagull/management/__init__.py
dseagull/management/commands/__init__.py
dseagull/management/commands/startmodel.py
dseagull-0.0.40.dist-info/licenses/LICENSE
dseagull-0.0.40.dist-info/METADATA
dseagull-0.0.40.dist-info/WHEEL
dseagull-0.0.40.dist-info/top_level.txt
dseagull-0.0.40.dist-info/RECORD
