Metadata-Version: 2.4
Name: dseagull
Version: 0.0.40
Summary: 快速构建 RESTful API
Author-email: chenhaiou <haiou_chen@sina.cn>
Classifier: Programming Language :: Python :: 3.12
Classifier: License :: OSI Approved :: MIT License
Classifier: Operating System :: OS Independent
Requires-Python: >=3.12.3
License-File: LICENSE
Requires-Dist: setuptools>=61.0
Requires-Dist: Django>=5.0.9
Requires-Dist: djangorestframework>=3.15.2
Requires-Dist: PyJWT>=2.9.0
Requires-Dist: django-cors-headers>=4.6.0
Requires-Dist: pymysql>=1.1.1
Requires-Dist: django-filter>=24.3
Requires-Dist: coreapi>=2.3.3
Requires-Dist: mysqlclient>=2.2.6
Requires-Dist: django-redis>=5.4.0
Dynamic: license-file
